README
setup.py
djoauth/__init__.py
djoauth/forms.py
djoauth/models.py
djoauth/tests.py
djoauth/views.py
djoauth.egg-info/PKG-INFO
djoauth.egg-info/SOURCES.txt
djoauth.egg-info/dependency_links.txt
djoauth.egg-info/top_level.txt