Metadata-Version: 1.0
Name: djoauth
Version: 0.1.3
Summary: Django application for oauth.
Home-page: http://pypi.python.org/pypi/djoauth/
Author: Jorge Eduardo Cardona
Author-email: jorgeecardona@gmail.com
License: BSD
Platform: UNKNOWN
